{
  "tool_name": "Bash",
  "tool_input_preview": "{\"command\":\"pnpm --filter @jobclaw/api typecheck 2>&1\",\"description\":\"Typecheck API to find build errors\"}",
  "error": "Exit code 2\n\n> @jobclaw/api@ typecheck /Users/hyungsukkang/hskang9/2026spring_41class_team7/apps/api\n> tsc -p tsconfig.json --noEmit\n\nsrc/lib/prisma.ts(2,10): error TS2305: Module '\"@prisma/client\"' has no exported member 'PrismaClient'.\nsrc/routes/assessments/list-assessments.handler.ts(28,24): error TS7006: Parameter 'r' implicitly has an 'any' type.\nsrc/routes/bootstrap/post-bootstrap.handler.ts(2,10): error TS2305: Module '\"@prisma/client\"' has no exported member 'Prisma'.\nsrc/routes/bootstr...",
  "timestamp": "2026-06-11T22:57:31.011Z",
  "retry_count": 1
}